{
  "project_info": {
    "project_number": "414897252488",
    "project_id": "ride-n-die",
    "storage_bucket": "ride-n-die.appspot.com"
  },
  "client": [
    {
      "client_info": {
        "mobilesdk_app_id": "1:414897252488:android:36704d5892c0d0aea4d73d",
        "android_client_info": {
          "package_name": "com.example.ride_n_die"
        }
      },
      "oauth_client": [],
      "api_key": [
        {
          "current_key": "AIzaSyBjutvECs4bkHDOhT1v1lNSesPRajiFgE8"
        }
      ],
      "services": {
        "appinvite_service": {
          "other_platform_oauth_client": []
        }
      }
    }
  ],
  "configuration_version": "1"
}